{"AFG":{"a2":"AF","area":652230,"borders":["IRN","PAK","TKM","UZB","TJK","CHN"],"languages":["Pashto","Uzbek","Turkmen"],"center":[33,65],"name":"Afghanistan","nativeName":"افغانستان","population":27657145,"region":"Asia","subregion":"Southern Asia","capital":"Kabul"},"ALA":{"a2":"AX","area":1580,"borders":[],"languages":["Swedish"],"center":[60.116667,19.9],"name":"Åland Islands","nativeName":"Åland","population":28875,"region":"Europe","subregion":"Northern Europe","capital":"Mariehamn","sovereignty":"FIN"},"ALB":{"a2":"AL","area":28748,"borders":["MNE","GRC","MKD","XKS"],"languages":["Albanian"],"center":[41,20],"name":"Albania","nativeName":"Shqipëria","population":2886026,"region":"Europe","subregion":"Southern Europe","capital":"Tirana"},"DZA":{"a2":"DZ","area":2381741,"borders":["TUN","LBY","NER","ESH","MRT","MLI","MAR"],"languages":["Arabic"],"center":[28,3],"name":"Algeria","nativeName":"الجزائر","population":40400000,"region":"Africa","subregion":"Northern Africa","capital":"Algiers"},"ASM":{"a2":"AS","area":199,"borders":[],"languages":["English","Samoan"],"center":[-14.33333333,-170],"name":"American Samoa","nativeName":"American Samoa","population":57100,"region":"Oceania","subregion":"Polynesia","capital":"Pago Pago","sovereignty":"USA"},"AND":{"a2":"AD","area":468,"borders":["FRA","ESP"],"languages":["Catalan"],"center":[42.5,1.5],"name":"Andorra","nativeName":"Andorra","population":78014,"region":"Europe","subregion":"Southern Europe","capital":"Andorra la Vella"},"AGO":{"a2":"AO","area":1246700,"borders":["COG","COD","ZMB","NAM"],"languages":["Portuguese"],"center":[-12.5,18.5],"name":"Angola","nativeName":"Angola","population":25868000,"region":"Africa","subregion":"Middle Africa","capital":"Luanda"},"AIA":{"a2":"AI","area":91,"borders":[],"languages":["English"],"center":[18.25,-63.16666666],"name":"Anguilla","nativeName":"Anguilla","population":13452,"region":"Americas","subregion":"Caribbean","capital":"The Valley","sovereignty":"GBR"},"ATA":{"a2":"AQ","area":14000000,"borders":[],"languages":["English","Russian"],"center":[-74.65,4.48],"name":"Antarctica","nativeName":"Antarctica","population":1000,"region":"Polar","subregion":"","capital":"","sovereignty":""},"ATG":{"a2":"AG","area":442,"borders":[],"languages":["English"],"center":[17.05,-61.8],"name":"Antigua and Barbuda","nativeName":"Antigua and Barbuda","population":86295,"region":"Americas","subregion":"Caribbean","capital":"St. John's"},"ARG":{"a2":"AR","area":2780400,"borders":["BOL","BRA","CHL","PRY","URY"],"languages":["Spanish","Guaraní"],"center":[-34,-64],"name":"Argentina","nativeName":"Argentina","population":43590400,"region":"Americas","subregion":"South America","capital":"Buenos Aires"},"ARM":{"a2":"AM","area":29743,"borders":["AZE","GEO","IRN","TUR"],"languages":["Armenian","Russian"],"center":[40,45],"name":"Armenia","nativeName":"Հայաստան","population":2994400,"region":"Asia","subregion":"Western Asia","capital":"Yerevan"},"ABW":{"a2":"AW","area":180,"borders":[],"languages":["Dutch","(Eastern) Punjabi"],"center":[12.5,-69.96666666],"name":"Aruba","nativeName":"Aruba","population":107394,"region":"Americas","subregion":"Caribbean","capital":"Oranjestad","sovereignty":"NLD"},"AUS":{"a2":"AU","area":7692024,"borders":[],"languages":["English"],"center":[-27,133],"name":"Australia","nativeName":"Australia","population":24117360,"region":"Oceania","subregion":"Australia and New Zealand","capital":"Canberra"},"AUT":{"a2":"AT","area":83871,"borders":["CZE","DEU","HUN","ITA","LIE","SVK","SVN","CHE"],"languages":["German"],"center":[47.33333333,13.33333333],"name":"Austria","nativeName":"Österreich","population":8725931,"region":"Europe","subregion":"Western Europe","capital":"Vienna"},"AZE":{"a2":"AZ","area":86600,"borders":["ARM","GEO","IRN","RUS","TUR"],"languages":["Azerbaijani"],"center":[40.5,47.5],"name":"Azerbaijan","nativeName":"Azərbaycan","population":9730500,"region":"Asia","subregion":"Western Asia","capital":"Baku"},"BHS":{"a2":"BS","area":13943,"borders":[],"languages":["English"],"center":[24.25,-76],"name":"Bahamas","nativeName":"Bahamas","population":378040,"region":"Americas","subregion":"Caribbean","capital":"Nassau"},"BHR":{"a2":"BH","area":765,"borders":[],"languages":["Arabic"],"center":[26,50.55],"name":"Bahrain","nativeName":"‏البحرين","population":1404900,"region":"Asia","subregion":"Western Asia","capital":"Manama"},"BGD":{"a2":"BD","area":147570,"borders":["MMR","IND"],"languages":["Bengali"],"center":[24,90],"name":"Bangladesh","nativeName":"Bangladesh","population":161006790,"region":"Asia","subregion":"Southern Asia","capital":"Dhaka"},"BRB":{"a2":"BB","area":430,"borders":[],"languages":["English"],"center":[13.16666666,-59.53333333],"name":"Barbados","nativeName":"Barbados","population":285000,"region":"Americas","subregion":"Caribbean","capital":"Bridgetown"},"BLR":{"a2":"BY","area":207600,"borders":["LVA","LTU","POL","RUS","UKR"],"languages":["Belarusian","Russian"],"center":[53,28],"name":"Belarus","nativeName":"Белару́сь","population":9498700,"region":"Europe","subregion":"Eastern Europe","capital":"Minsk"},"BEL":{"a2":"BE","area":30528,"borders":["FRA","DEU","LUX","NLD"],"languages":["Dutch","French","German"],"center":[50.83333333,4],"name":"Belgium","nativeName":"België","population":11319511,"region":"Europe","subregion":"Western Europe","capital":"Brussels"},"BLZ":{"a2":"BZ","area":22966,"borders":["GTM","MEX"],"languages":["English","Spanish"],"center":[17.25,-88.75],"name":"Belize","nativeName":"Belize","population":370300,"region":"Americas","subregion":"Central America","capital":"Belmopan"},"BEN":{"a2":"BJ","area":112622,"borders":["BFA","NER","NGA","TGO"],"languages":["French"],"center":[9.5,2.25],"name":"Benin","nativeName":"Bénin","population":10653654,"region":"Africa","subregion":"Western Africa","capital":"Porto-Novo"},"BMU":{"a2":"BM","area":54,"borders":[],"languages":["English"],"center":[32.33333333,-64.75],"name":"Bermuda","nativeName":"Bermuda","population":61954,"region":"Americas","subregion":"Northern America","capital":"Hamilton","sovereignty":"GBR"},"BTN":{"a2":"BT","area":38394,"borders":["CHN","IND"],"languages":["Dzongkha"],"center":[27.5,90.5],"name":"Bhutan","nativeName":"ʼbrug-yul","population":775620,"region":"Asia","subregion":"Southern Asia","capital":"Thimphu"},"BOL":{"a2":"BO","area":1098581,"borders":["ARG","BRA","CHL","PRY","PER"],"languages":["Spanish","Aymara","Quechua"],"center":[-17,-65],"name":"Bolivia","nativeName":"Bolivia","population":10985059,"region":"Americas","subregion":"South America","capital":"Sucre"},"BES":{"a2":"BQ","area":294,"borders":[],"languages":["Dutch"],"center":[12.15,-68.266667],"name":"Bonaire, Saint Eustatius and Saba","nativeName":"Bonaire","population":17408,"region":"Americas","subregion":"Caribbean","capital":"Kralendijk","sovereignty":"NLD"},"BIH":{"a2":"BA","area":51209,"borders":["HRV","MNE","SRB"],"languages":["Bosnian","Croatian","Serbian"],"center":[44,18],"name":"Bosnia and Herzegovina","nativeName":"Bosna i Hercegovina","population":3531159,"region":"Europe","subregion":"Southern Europe","capital":"Sarajevo"},"BWA":{"a2":"BW","area":582000,"borders":["NAM","ZAF","ZMB","ZWE"],"languages":["English","Tswana"],"center":[-22,24],"name":"Botswana","nativeName":"Botswana","population":2141206,"region":"Africa","subregion":"Southern Africa","capital":"Gaborone"},"BVT":{"a2":"BV","area":49,"borders":[],"languages":["Norwegian","Norwegian Bokmål","Norwegian Nynorsk"],"center":[-54.43333333,3.4],"name":"Bouvet Island","nativeName":"Bouvetøya","population":0,"region":"Polar","subregion":"Polar","capital":"","sovereignty":"NOR"},"BRA":{"a2":"BR","area":8515767,"borders":["ARG","BOL","COL","GUF","GUY","PRY","PER","SUR","URY","VEN"],"languages":["Portuguese"],"center":[-10,-55],"name":"Brazil","nativeName":"Brasil","population":206135893,"region":"Americas","subregion":"South America","capital":"Brasilia"},"IOT":{"a2":"IO","area":60,"borders":[],"languages":["English"],"center":[-6,71.5],"name":"British Indian Ocean Territory","nativeName":"British Indian Ocean Territory","population":3000,"region":"Africa","subregion":"Eastern Africa","capital":"Diego Garcia","sovereignty":"GBR"},"VGB":{"a2":"VG","area":151,"borders":[],"languages":["English"],"center":[18.431383,-64.62305],"name":"Virgin Islands (British)","nativeName":"British Virgin Islands","population":28514,"region":"Americas","subregion":"Caribbean","capital":"Road Town","sovereignty":"GBR"},"VIR":{"a2":"VI","area":346.36,"borders":[],"languages":["English"],"center":[18.34,-64.93],"name":"Virgin Islands (U.S.)","nativeName":"Virgin Islands of the United States","population":114743,"region":"Americas","subregion":"Caribbean","capital":"Charlotte Amalie","sovereignty":"USA"},"BRN":{"a2":"BN","area":5765,"borders":["MYS"],"languages":["Malay"],"center":[4.5,114.66666666],"name":"Brunei","nativeName":"Negara Brunei","population":411900,"region":"Asia","subregion":"South-Eastern Asia","capital":"Bandar Seri Begawan"},"BGR":{"a2":"BG","area":110879,"borders":["GRC","MKD","ROU","SRB","TUR"],"languages":["Bulgarian"],"center":[43,25],"name":"Bulgaria","nativeName":"България","population":7153784,"region":"Europe","subregion":"Eastern Europe","capital":"Sofia"},"BFA":{"a2":"BF","area":272967,"borders":["BEN","CIV","GHA","MLI","NER","TGO"],"languages":["French","Fula"],"center":[13,-2],"name":"Burkina Faso","nativeName":"Burkina Faso","population":19034397,"region":"Africa","subregion":"Western Africa","capital":"Ouagadougou"},"BDI":{"a2":"BI","area":27834,"borders":["COD","RWA","TZA"],"languages":["French","Kirundi"],"center":[-3.5,30],"name":"Burundi","nativeName":"Burundi","population":10114505,"region":"Africa","subregion":"Eastern Africa","capital":"Bujumbura"},"KHM":{"a2":"KH","area":181035,"borders":["LAO","THA","VNM"],"languages":["Khmer"],"center":[13,105],"name":"Cambodia","nativeName":"Kâmpŭchéa","population":15626444,"region":"Asia","subregion":"South-Eastern Asia","capital":"Phnom Penh"},"CMR":{"a2":"CM","area":475442,"borders":["CAF","TCD","COG","GNQ","GAB","NGA"],"languages":["English","French"],"center":[6,12],"name":"Cameroon","nativeName":"Cameroon","population":22709892,"region":"Africa","subregion":"Middle Africa","capital":"Yaounde"},"CAN":{"a2":"CA","area":9984670,"borders":["USA"],"languages":["English","French"],"center":[60,-95],"name":"Canada","nativeName":"Canada","population":36155487,"region":"Americas","subregion":"Northern America","capital":"Ottawa"},"CPV":{"a2":"CV","area":4033,"borders":[],"languages":["Portuguese"],"center":[16,-24],"name":"Cape Verde","nativeName":"Cape Verde","population":531239,"region":"Africa","subregion":"Western Africa","capital":"Praia"},"CYM":{"a2":"KY","area":264,"borders":[],"languages":["English"],"center":[19.5,-80.5],"name":"Cayman Islands","nativeName":"Cayman Islands","population":58238,"region":"Americas","subregion":"Caribbean","capital":"George Town","sovereignty":"GBR"},"CAF":{"a2":"CF","area":622984,"borders":["CMR","TCD","COD","COG","SSD","SDN"],"languages":["French","Sango"],"center":[7,21],"name":"Central African Republic","nativeName":"Ködörösêse tî Bêafrîka","population":4998000,"region":"Africa","subregion":"Middle Africa","capital":"Bangui"},"TCD":{"a2":"TD","area":1284000,"borders":["CMR","CAF","LBY","NER","NGA","SSD"],"languages":["French","Arabic"],"center":[15,19],"name":"Chad","nativeName":"Tchad","population":14497000,"region":"Africa","subregion":"Middle Africa","capital":"N'Djamena"},"CHL":{"a2":"CL","area":756102,"borders":["ARG","BOL","PER"],"languages":["Spanish"],"center":[-30,-71],"name":"Chile","nativeName":"Chile","population":18191900,"region":"Americas","subregion":"South America","capital":"Santiago"},"CHN":{"a2":"CN","area":9640011,"borders":["AFG","BTN","MMR","HKG","IND","KAZ","PRK","KGZ","LAO","MAC","MNG","PAK","RUS","TJK","VNM"],"languages":["Chinese"],"center":[35,105],"name":"China","nativeName":"中国","population":1377422166,"region":"Asia","subregion":"Eastern Asia","capital":"Beijing"},"CXR":{"a2":"CX","area":135,"borders":[],"languages":["English"],"center":[-10.5,105.66666666],"name":"Christmas Island","nativeName":"Christmas Island","population":2072,"region":"Oceania","subregion":"Australia and New Zealand","capital":"Flying Fish Cove","sovereignty":"AUS"},"CCK":{"a2":"CC","area":14,"borders":[],"languages":["English"],"center":[-12.5,96.83333333],"name":"Cocos Islands","nativeName":"Cocos (Keeling) Islands","population":550,"region":"Oceania","subregion":"Australia and New Zealand","capital":"West Island","sovereignty":"AUS"},"COL":{"a2":"CO","area":1141748,"borders":["BRA","ECU","PAN","PER","VEN"],"languages":["Spanish"],"center":[4,-72],"name":"Colombia","nativeName":"Colombia","population":48759958,"region":"Americas","subregion":"South America","capital":"Bogota"},"COM":{"a2":"KM","area":1862,"borders":[],"languages":["Arabic","French"],"center":[-12.16666666,44.25],"name":"Comoros","nativeName":"Komori","population":806153,"region":"Africa","subregion":"Eastern Africa","capital":"Moroni"},"COG":{"a2":"CG","area":342000,"borders":["AGO","CMR","CAF","COD","GAB"],"languages":["French","Lingala"],"center":[-1,15],"name":"Congo","nativeName":"République du Congo","population":4741000,"region":"Africa","subregion":"Middle Africa","capital":"Brazzaville"},"COD":{"a2":"CD","area":2344858,"borders":["AGO","BDI","CAF","COG","RWA","SSD","TZA","UGA","ZMB"],"languages":["French","Lingala","Kongo","Swahili","Luba-Katanga"],"center":[0,25],"name":"Democratic Republic of the Congo","nativeName":"République démocratique du Congo","population":85026000,"region":"Africa","subregion":"Middle Africa","capital":"Kinshasa"},"COK":{"a2":"CK","area":236,"borders":[],"languages":["English"],"center":[-21.23333333,-159.76666666],"name":"Cook Islands","nativeName":"Cook Islands","population":18100,"region":"Oceania","subregion":"Polynesia","capital":"Avarua","sovereignty":"NZL"},"CRI":{"a2":"CR","area":51100,"borders":["NIC","PAN"],"languages":["Spanish"],"center":[10,-84],"name":"Costa Rica","nativeName":"Costa Rica","population":4890379,"region":"Americas","subregion":"Central America","capital":"San Jose"},"HRV":{"a2":"HR","area":56594,"borders":["BIH","HUN","MNE","SRB","SVN"],"languages":["Croatian"],"center":[45.16666666,15.5],"name":"Croatia","nativeName":"Hrvatska","population":4190669,"region":"Europe","subregion":"Southern Europe","capital":"Zagreb"},"CUB":{"a2":"CU","area":109884,"borders":[],"languages":["Spanish"],"center":[21.5,-80],"name":"Cuba","nativeName":"Cuba","population":11239004,"region":"Americas","subregion":"Caribbean","capital":"Havana"},"CUW":{"a2":"CW","area":444,"borders":[],"languages":["Dutch","(Eastern) Punjabi","English"],"center":[12.116667,-68.933333],"name":"Curaçao","nativeName":"Curaçao","population":154843,"region":"Americas","subregion":"Caribbean","capital":" Willemstad","sovereignty":"NLD"},"CYP":{"a2":"CY","area":9251,"borders":["GBR"],"languages":["Greek (modern)","Turkish","Armenian"],"center":[35,33],"name":"Cyprus","nativeName":"Κύπρος","population":847000,"region":"Europe","subregion":"Southern Europe","capital":"Nicosia"},"CZE":{"a2":"CZ","area":78865,"borders":["AUT","DEU","POL","SVK"],"languages":["Czech","Slovak"],"center":[49.75,15.5],"name":"Czechia","nativeName":"Česká republika","population":10558524,"region":"Europe","subregion":"Eastern Europe","capital":"Prague"},"DNK":{"a2":"DK","area":43094,"borders":["DEU"],"languages":["Danish"],"center":[56,10],"name":"Denmark","nativeName":"Danmark","population":5717014,"region":"Europe","subregion":"Northern Europe","capital":"Copenhagen"},"DJI":{"a2":"DJ","area":23200,"borders":["ERI","ETH","SOM"],"languages":["French","Arabic"],"center":[11.5,43],"name":"Djibouti","nativeName":"Djibouti","population":900000,"region":"Africa","subregion":"Eastern Africa","capital":"Djibouti"},"DMA":{"a2":"DM","area":751,"borders":[],"languages":["English"],"center":[15.41666666,-61.33333333],"name":"Dominica","nativeName":"Dominica","population":71293,"region":"Americas","subregion":"Caribbean","capital":"Roseau"},"DOM":{"a2":"DO","area":48671,"borders":["HTI"],"languages":["Spanish"],"center":[19,-70.66666666],"name":"Dominican Republic","nativeName":"República Dominicana","population":10075045,"region":"Americas","subregion":"Caribbean","capital":"Santo Domingo"},"ECU":{"a2":"EC","area":276841,"borders":["COL","PER"],"languages":["Spanish"],"center":[-2,-77.5],"name":"Ecuador","nativeName":"Ecuador","population":16545799,"region":"Americas","subregion":"South America","capital":"Quito"},"EGY":{"a2":"EG","area":1002450,"borders":["ISR","LBY","SDN"],"languages":["Arabic"],"center":[27,30],"name":"Egypt","nativeName":"مصر‎","population":91290000,"region":"Africa","subregion":"Northern Africa","capital":"Cairo"},"SLV":{"a2":"SV","area":21041,"borders":["GTM","HND"],"languages":["Spanish"],"center":[13.83333333,-88.91666666],"name":"El Salvador","nativeName":"El Salvador","population":6520675,"region":"Americas","subregion":"Central America","capital":"San Salvador"},"GNQ":{"a2":"GQ","area":28051,"borders":["CMR","GAB"],"languages":["Spanish","French"],"center":[2,10],"name":"Equatorial Guinea","nativeName":"Guinea Ecuatorial","population":1222442,"region":"Africa","subregion":"Middle Africa","capital":"Malabo"},"ERI":{"a2":"ER","area":117600,"borders":["DJI","ETH","SDN"],"languages":["Tigrinya","Arabic","English"],"center":[15,39],"name":"Eritrea","nativeName":"ኤርትራ","population":5352000,"region":"Africa","subregion":"Eastern Africa","capital":"Asmara"},"EST":{"a2":"EE","area":45227,"borders":["LVA","RUS"],"languages":["Estonian"],"center":[59,26],"name":"Estonia","nativeName":"Eesti","population":1315944,"region":"Europe","subregion":"Northern Europe","capital":"Tallinn"},"ETH":{"a2":"ET","area":1104300,"borders":["DJI","ERI","KEN","SOM","SSD","SDN"],"languages":["Amharic"],"center":[8,38],"name":"Ethiopia","nativeName":"ኢትዮጵያ","population":92206005,"region":"Africa","subregion":"Eastern Africa","capital":"Addis Ababa"},"FLK":{"a2":"FK","area":12173,"borders":[],"languages":["English"],"center":[-51.75,-59],"name":"Falkland Islands","nativeName":"Falkland Islands","population":2563,"region":"Americas","subregion":"South America","capital":"Stanley","sovereignty":"GBR"},"FRO":{"a2":"FO","area":1393,"borders":[],"languages":["Faroese"],"center":[62,-7],"name":"Faroe Islands","nativeName":"Føroyar","population":49376,"region":"Europe","subregion":"Northern Europe","capital":"Torshavn","sovereignty":"DNK"},"FJI":{"a2":"FJ","area":18272,"borders":[],"languages":["English","Fijian","Hindi","Urdu"],"center":[-18,175],"name":"Fiji","nativeName":"Fiji","population":867000,"region":"Oceania","subregion":"Melanesia","capital":"Suva"},"FIN":{"a2":"FI","area":338424,"borders":["NOR","SWE","RUS"],"languages":["Finnish","Swedish"],"center":[64,26],"name":"Finland","nativeName":"Suomi","population":5491817,"region":"Europe","subregion":"Northern Europe","capital":"Helsinki"},"FRA":{"a2":"FR","area":640679,"borders":["AND","BEL","DEU","ITA","LUX","MCO","ESP","CHE"],"languages":["French"],"center":[46,2],"name":"France","nativeName":"France","population":66710000,"region":"Europe","subregion":"Western Europe","capital":"Paris"},"GUF":{"a2":"GF","area":null,"borders":["BRA","SUR"],"languages":["French"],"center":[4,-53],"name":"French Guiana","nativeName":"Guyane française","population":254541,"region":"Americas","subregion":"South America","capital":"Cayenne","sovereignty":"FRA"},"PYF":{"a2":"PF","area":4167,"borders":[],"languages":["French"],"center":[-15,-140],"name":"French Polynesia","nativeName":"Polynésie française","population":271800,"region":"Oceania","subregion":"Polynesia","capital":"Papeete","sovereignty":"FRA"},"ATF":{"a2":"TF","area":7747,"borders":[],"languages":["French"],"center":[-49.25,69.167],"name":"French Southern Territories","nativeName":"Territoire des Terres australes et antarctiques françaises","population":140,"region":"Africa","subregion":"Southern Africa","capital":"Port-aux-Francais","sovereignty":"FRA"},"GAB":{"a2":"GA","area":267668,"borders":["CMR","COG","GNQ"],"languages":["French"],"center":[-1,11.75],"name":"Gabon","nativeName":"Gabon","population":1802278,"region":"Africa","subregion":"Middle Africa","capital":"Libreville"},"GMB":{"a2":"GM","area":11295,"borders":["SEN"],"languages":["English"],"center":[13.46666666,-16.56666666],"name":"Gambia","nativeName":"Gambia","population":1882450,"region":"Africa","subregion":"Western Africa","capital":"Banjul"},"GEO":{"a2":"GE","area":69700,"borders":["ARM","AZE","RUS","TUR"],"languages":["Georgian"],"center":[42,43.5],"name":"Georgia","nativeName":"საქართველო","population":3720400,"region":"Asia","subregion":"Western Asia","capital":"Tbilisi"},"DEU":{"a2":"DE","area":357114,"borders":["AUT","BEL","CZE","DNK","FRA","LUX","NLD","POL","CHE"],"languages":["German"],"center":[51,9],"name":"Germany","nativeName":"Deutschland","population":81770900,"region":"Europe","subregion":"Western Europe","capital":"Berlin"},"GHA":{"a2":"GH","area":238533,"borders":["BFA","CIV","TGO"],"languages":["English"],"center":[8,-2],"name":"Ghana","nativeName":"Ghana","population":27670174,"region":"Africa","subregion":"Western Africa","capital":"Accra"},"GIB":{"a2":"GI","area":6,"borders":["ESP"],"languages":["English"],"center":[36.13333333,-5.35],"name":"Gibraltar","nativeName":"Gibraltar","population":33140,"region":"Europe","subregion":"Southern Europe","capital":"Gibraltar","sovereignty":"GBR"},"GRC":{"a2":"GR","area":131990,"borders":["ALB","BGR","TUR","MKD"],"languages":["Greek (modern)"],"center":[39,22],"name":"Greece","nativeName":"Ελλάδα","population":10858018,"region":"Europe","subregion":"Southern Europe","capital":"Athens"},"GRL":{"a2":"GL","area":2166086,"borders":[],"languages":["Kalaallisut"],"center":[72,-40],"name":"Greenland","nativeName":"Kalaallit Nunaat","population":55847,"region":"Americas","subregion":"Northern America","capital":"Nuuk","sovereignty":"DNK"},"GRD":{"a2":"GD","area":344,"borders":[],"languages":["English"],"center":[12.11666666,-61.66666666],"name":"Grenada","nativeName":"Grenada","population":103328,"region":"Americas","subregion":"Caribbean","capital":"St. George's"},"GLP":{"a2":"GP","area":null,"borders":[],"languages":["French"],"center":[16.25,-61.583333],"name":"Guadeloupe","nativeName":"Guadeloupe","population":400132,"region":"Americas","subregion":"Caribbean","capital":"Basse-Terre","sovereignty":"FRA"},"GUM":{"a2":"GU","area":549,"borders":[],"languages":["English","Chamorro","Spanish"],"center":[13.46666666,144.78333333],"name":"Guam","nativeName":"Guam","population":184200,"region":"Oceania","subregion":"Micronesia","capital":"Hagatna","sovereignty":"USA"},"GTM":{"a2":"GT","area":108889,"borders":["BLZ","SLV","HND","MEX"],"languages":["Spanish"],"center":[15.5,-90.25],"name":"Guatemala","nativeName":"Guatemala","population":16176133,"region":"Americas","subregion":"Central America","capital":"Guatemala City"},"GGY":{"a2":"GG","area":78,"borders":[],"languages":["English","French"],"center":[49.46666666,-2.58333333],"name":"Guernsey","nativeName":"Guernsey","population":62999,"region":"Europe","subregion":"Northern Europe","capital":"St Peter Port","sovereignty":"GBR"},"GIN":{"a2":"GN","area":245857,"borders":["CIV","GNB","LBR","MLI","SEN","SLE"],"languages":["French","Fula"],"center":[11,-10],"name":"Guinea","nativeName":"Guinée","population":12947000,"region":"Africa","subregion":"Western Africa","capital":"Conakry"},"GNB":{"a2":"GW","area":36125,"borders":["GIN","SEN"],"languages":["Portuguese"],"center":[12,-15],"name":"Guinea-Bissau","nativeName":"Guiné-Bissau","population":1547777,"region":"Africa","subregion":"Western Africa","capital":"Bissau"},"GUY":{"a2":"GY","area":214969,"borders":["BRA","SUR","VEN"],"languages":["English"],"center":[5,-59],"name":"Guyana","nativeName":"Guyana","population":746900,"region":"Americas","subregion":"South America","capital":"Georgetown"},"HTI":{"a2":"HT","area":27750,"borders":["DOM"],"languages":["French","Haitian"],"center":[19,-72.41666666],"name":"Haiti","nativeName":"Haïti","population":11078033,"region":"Americas","subregion":"Caribbean","capital":"Port-au-Prince"},"HMD":{"a2":"HM","area":412,"borders":[],"languages":["English"],"center":[-53.1,72.51666666],"name":"Heard Island and McDonald Islands","nativeName":"Heard Island and McDonald Islands","population":0,"region":"Africa","subregion":"Southern Africa","capital":"","sovereignty":"AUS"},"VAT":{"a2":"VA","area":0.44,"borders":["ITA"],"languages":["Latin","Italian","French","German"],"center":[41.9,12.45],"name":"Holy See","nativeName":"Sancta Sedes","population":451,"region":"Europe","subregion":"Southern Europe","capital":"Vatican City"},"HND":{"a2":"HN","area":112492,"borders":["GTM","SLV","NIC"],"languages":["Spanish"],"center":[15,-86.5],"name":"Honduras","nativeName":"Honduras","population":8576532,"region":"Americas","subregion":"Central America","capital":"Tegucigalpa"},"HKG":{"a2":"HK","area":1104,"borders":["CHN"],"languages":["English","Chinese"],"center":[22.25,114.16666666],"name":"Hong Kong","nativeName":"香港","population":7324300,"region":"Asia","subregion":"Eastern Asia","capital":"Hong Kong","sovereignty":"CHN"},"HUN":{"a2":"HU","area":93028,"borders":["AUT","HRV","ROU","SRB","SVK","SVN","UKR"],"languages":["Hungarian"],"center":[47,20],"name":"Hungary","nativeName":"Magyarország","population":9823000,"region":"Europe","subregion":"Eastern Europe","capital":"Budapest"},"ISL":{"a2":"IS","area":103000,"borders":[],"languages":["Icelandic"],"center":[65,-18],"name":"Iceland","nativeName":"Ísland","population":334300,"region":"Europe","subregion":"Northern Europe","capital":"Reykjavik"},"IND":{"a2":"IN","area":3287590,"borders":["AFG","BGD","BTN","MMR","CHN","NPL","PAK","LKA"],"languages":["Hindi","English"],"center":[20,77],"name":"India","nativeName":"भारत","population":1295210000,"region":"Asia","subregion":"Southern Asia","capital":"New Delhi"},"IDN":{"a2":"ID","area":1904569,"borders":["TLS","MYS","PNG"],"languages":["Indonesian"],"center":[-5,120],"name":"Indonesia","nativeName":"Indonesia","population":258705000,"region":"Asia","subregion":"South-Eastern Asia","capital":"Jakarta"},"CIV":{"a2":"CI","area":322463,"borders":["BFA","GHA","GIN","LBR","MLI"],"languages":["French"],"center":[8,-5],"name":"Côte d'Ivoire","nativeName":"Côte d'Ivoire","population":22671331,"region":"Africa","subregion":"Western Africa","capital":"Yamoussoukro"},"IRN":{"a2":"IR","area":1648195,"borders":["AFG","ARM","AZE","IRQ","PAK","TUR","TKM"],"languages":["Persian (Farsi)"],"center":[32,53],"name":"Iran","nativeName":"ایران","population":79369900,"region":"Asia","subregion":"Southern Asia","capital":"Tehran"},"IRQ":{"a2":"IQ","area":438317,"borders":["IRN","JOR","KWT","SAU","SYR","TUR"],"languages":["Arabic","Kurdish"],"center":[33,44],"name":"Iraq","nativeName":"العراق","population":37883543,"region":"Asia","subregion":"Western Asia","capital":"Baghdad"},"IRL":{"a2":"IE","area":70273,"borders":["GBR"],"languages":["Irish","English"],"center":[53,-8],"name":"Ireland","nativeName":"Éire","population":6378000,"region":"Europe","subregion":"Northern Europe","capital":"Dublin"},"IMN":{"a2":"IM","area":572,"borders":[],"languages":["English","Manx"],"center":[54.25,-4.5],"name":"Isle of Man","nativeName":"Isle of Man","population":84497,"region":"Europe","subregion":"Northern Europe","capital":"Douglas","sovereignty":"GBR"},"ISR":{"a2":"IL","area":20770,"borders":["EGY","JOR","LBN","SYR"],"languages":["Hebrew (modern)","Arabic"],"center":[31.5,34.75],"name":"Israel","nativeName":"יִשְׂרָאֵל","population":8527400,"region":"Asia","subregion":"Western Asia","capital":"Jerusalem"},"ITA":{"a2":"IT","area":301336,"borders":["AUT","FRA","SMR","SVN","CHE","VAT"],"languages":["Italian"],"center":[42.83333333,12.83333333],"name":"Italy","nativeName":"Italia","population":60665551,"region":"Europe","subregion":"Southern Europe","capital":"Rome"},"JAM":{"a2":"JM","area":10991,"borders":[],"languages":["English"],"center":[18.25,-77.5],"name":"Jamaica","nativeName":"Jamaica","population":2723246,"region":"Americas","subregion":"Caribbean","capital":"Kingston"},"JPN":{"a2":"JP","area":377930,"borders":[],"languages":["Japanese"],"center":[36,138],"name":"Japan","nativeName":"日本","population":126960000,"region":"Asia","subregion":"Eastern Asia","capital":"Tokyo"},"JEY":{"a2":"JE","area":116,"borders":[],"languages":["English","French"],"center":[49.25,-2.16666666],"name":"Jersey","nativeName":"Jersey","population":100800,"region":"Europe","subregion":"Northern Europe","capital":"Saint Helier","sovereignty":"GBR"},"JOR":{"a2":"JO","area":89342,"borders":["IRQ","ISR","SAU","SYR"],"languages":["Arabic"],"center":[31,36],"name":"Jordan","nativeName":"الأردن","population":9531712,"region":"Asia","subregion":"Western Asia","capital":"Amman"},"KAZ":{"a2":"KZ","area":2724900,"borders":["CHN","KGZ","RUS","TKM","UZB"],"languages":["Kazakh","Russian"],"center":[48,68],"name":"Kazakhstan","nativeName":"Қазақстан","population":17753200,"region":"Asia","subregion":"Central Asia","capital":"Astana"},"KEN":{"a2":"KE","area":580367,"borders":["ETH","SOM","SSD","TZA","UGA"],"languages":["English","Swahili"],"center":[1,38],"name":"Kenya","nativeName":"Kenya","population":47251000,"region":"Africa","subregion":"Eastern Africa","capital":"Nairobi"},"KIR":{"a2":"KI","area":811,"borders":[],"languages":["English"],"center":[1.41666666,173],"name":"Kiribati","nativeName":"Kiribati","population":113400,"region":"Oceania","subregion":"Micronesia","capital":"Tarawa"},"KWT":{"a2":"KW","area":17818,"borders":["IRN","SAU"],"languages":["Arabic"],"center":[29.5,45.75],"name":"Kuwait","nativeName":"الكويت","population":4183658,"region":"Asia","subregion":"Western Asia","capital":"Kuwait City"},"KGZ":{"a2":"KG","area":199951,"borders":["CHN","KAZ","TJK","UZB"],"languages":["Kyrgyz","Russian"],"center":[41,75],"name":"Kyrgyzstan","nativeName":"Кыргызстан","population":6047800,"region":"Asia","subregion":"Central Asia","capital":"Bishkek"},"LAO":{"a2":"LA","area":236800,"borders":["MMR","KHM","CHN","THA","VNM"],"languages":["Lao"],"center":[18,105],"name":"Laos","nativeName":"ສປປລາວ","population":6492400,"region":"Asia","subregion":"South-Eastern Asia","capital":"Vientiane"},"LVA":{"a2":"LV","area":64559,"borders":["BLR","EST","LTU","RUS"],"languages":["Latvian"],"center":[57,25],"name":"Latvia","nativeName":"Latvija","population":1961600,"region":"Europe","subregion":"Northern Europe","capital":"Riga"},"LBN":{"a2":"LB","area":10452,"borders":["ISR","SYR"],"languages":["Arabic","French"],"center":[33.83333333,35.83333333],"name":"Lebanon","nativeName":"لبنان","population":5988000,"region":"Asia","subregion":"Western Asia","capital":"Beirut"},"LSO":{"a2":"LS","area":30355,"borders":["ZAF"],"languages":["English","Southern Sotho"],"center":[-29.5,28.5],"name":"Lesotho","nativeName":"Lesotho","population":1894194,"region":"Africa","subregion":"Southern Africa","capital":"Maseru"},"LBR":{"a2":"LR","area":111369,"borders":["GIN","CIV","SLE"],"languages":["English"],"center":[6.5,-9.5],"name":"Liberia","nativeName":"Liberia","population":4615000,"region":"Africa","subregion":"Western Africa","capital":"Monrovia"},"LBY":{"a2":"LY","area":1759540,"borders":["DZA","TCD","EGY","NER","SDN","TUN"],"languages":["Arabic"],"center":[25,17],"name":"Libya","nativeName":"‏ليبيا","population":6385000,"region":"Africa","subregion":"Northern Africa","capital":"Tripolis"},"LIE":{"a2":"LI","area":160,"borders":["AUT","CHE"],"languages":["German"],"center":[47.26666666,9.53333333],"name":"Liechtenstein","nativeName":"Liechtenstein","population":37623,"region":"Europe","subregion":"Western Europe","capital":"Vaduz"},"LTU":{"a2":"LT","area":65300,"borders":["BLR","LVA","POL","RUS"],"languages":["Lithuanian"],"center":[56,24],"name":"Lithuania","nativeName":"Lietuva","population":2872294,"region":"Europe","subregion":"Northern Europe","capital":"Vilnius"},"LUX":{"a2":"LU","area":2586,"borders":["BEL","FRA","DEU"],"languages":["French","German","Luxembourgish"],"center":[49.75,6.16666666],"name":"Luxembourg","nativeName":"Luxembourg","population":576200,"region":"Europe","subregion":"Western Europe","capital":"Luxembourg"},"MAC":{"a2":"MO","area":30,"borders":["CHN"],"languages":["Chinese","Portuguese"],"center":[22.16666666,113.55],"name":"Macao","nativeName":"澳門","population":649100,"region":"Asia","subregion":"Eastern Asia","capital":"Macao","sovereignty":"CHN"},"MKD":{"a2":"MK","area":25713,"borders":["ALB","BGR","GRC","XKS","SRB"],"languages":["Macedonian"],"center":[41.83333333,22],"name":"North Macedonia","nativeName":"Македонија","population":2058539,"region":"Europe","subregion":"Southern Europe","capital":"Skopje"},"MDG":{"a2":"MG","area":587041,"borders":[],"languages":["French","Malagasy"],"center":[-20,47],"name":"Madagascar","nativeName":"Madagasikara","population":22434363,"region":"Africa","subregion":"Eastern Africa","capital":"Antananarivo"},"MWI":{"a2":"MW","area":118484,"borders":["MOZ","TZA","ZMB"],"languages":["English","Chichewa"],"center":[-13.5,34],"name":"Malawi","nativeName":"Malawi","population":16832910,"region":"Africa","subregion":"Eastern Africa","capital":"Lilongwe"},"MYS":{"a2":"MY","area":330803,"borders":["BRN","IDN","THA"],"languages":["Malaysian"],"center":[2.5,112.5],"name":"Malaysia","nativeName":"Malaysia","population":31405416,"region":"Asia","subregion":"South-Eastern Asia","capital":"Kuala Lumpur"},"MDV":{"a2":"MV","area":300,"borders":[],"languages":["Divehi"],"center":[3.25,73],"name":"Maldives","nativeName":"Maldives","population":344023,"region":"Asia","subregion":"Southern Asia","capital":"Male"},"MLI":{"a2":"ML","area":1240192,"borders":["DZA","BFA","GIN","CIV","MRT","NER","SEN"],"languages":["French"],"center":[17,-4],"name":"Mali","nativeName":"Mali","population":18135000,"region":"Africa","subregion":"Western Africa","capital":"Bamako"},"MLT":{"a2":"MT","area":316,"borders":[],"languages":["Maltese","English"],"center":[35.83333333,14.58333333],"name":"Malta","nativeName":"Malta","population":425384,"region":"Europe","subregion":"Southern Europe","capital":"Valletta"},"MHL":{"a2":"MH","area":181,"borders":[],"languages":["English","Marshallese"],"center":[9,168],"name":"Marshall Islands","nativeName":"M̧ajeļ","population":54880,"region":"Oceania","subregion":"Micronesia","capital":"Majuro"},"MTQ":{"a2":"MQ","area":null,"borders":[],"languages":["French"],"center":[14.666667,-61],"name":"Martinique","nativeName":"Martinique","population":378243,"region":"Americas","subregion":"Caribbean","capital":"Fort-de-France","sovereignty":"FRA"},"MRT":{"a2":"MR","area":1030700,"borders":["DZA","MLI","SEN","ESH"],"languages":["Arabic"],"center":[20,-12],"name":"Mauritania","nativeName":"موريتانيا","population":3718678,"region":"Africa","subregion":"Western Africa","capital":"Nouakchott"},"MUS":{"a2":"MU","area":2040,"borders":[],"languages":["English"],"center":[-20.28333333,57.55],"name":"Mauritius","nativeName":"Maurice","population":1262879,"region":"Africa","subregion":"Eastern Africa","capital":"Port Louis"},"MYT":{"a2":"YT","area":null,"borders":[],"languages":["French"],"center":[-12.83333333,45.16666666],"name":"Mayotte","nativeName":"Mayotte","population":226915,"region":"Africa","subregion":"Eastern Africa","capital":"Mamoudzou","sovereignty":"FRA"},"MEX":{"a2":"MX","area":1964375,"borders":["BLZ","GTM","USA"],"languages":["Spanish"],"center":[23,-102],"name":"Mexico","nativeName":"México","population":122273473,"region":"Americas","subregion":"Central America","capital":"Mexico City"},"FSM":{"a2":"FM","area":702,"borders":[],"languages":["English"],"center":[6.91666666,158.25],"name":"Micronesia","nativeName":"Micronesia","population":102800,"region":"Oceania","subregion":"Micronesia","capital":"Palikir"},"MDA":{"a2":"MD","area":33846,"borders":["ROU","UKR"],"languages":["Romanian"],"center":[47,29],"name":"Moldova","nativeName":"Moldova","population":3553100,"region":"Europe","subregion":"Eastern Europe","capital":"Chisinau"},"MCO":{"a2":"MC","area":2.02,"borders":["FRA"],"languages":["French"],"center":[43.73333333,7.4],"name":"Monaco","nativeName":"Monaco","population":38400,"region":"Europe","subregion":"Western Europe","capital":"Monaco"},"MNG":{"a2":"MN","area":1564110,"borders":["CHN","RUS"],"languages":["Mongolian"],"center":[46,105],"name":"Mongolia","nativeName":"Монгол улс","population":3093100,"region":"Asia","subregion":"Eastern Asia","capital":"Ulan Bator"},"MNE":{"a2":"ME","area":13812,"borders":["ALB","BIH","HRV","XKS","SRB"],"languages":["Serbian","Bosnian","Albanian","Croatian"],"center":[42.5,19.3],"name":"Montenegro","nativeName":"Црна Гора","population":621810,"region":"Europe","subregion":"Southern Europe","capital":"Podgorica"},"MSR":{"a2":"MS","area":102,"borders":[],"languages":["English"],"center":[16.75,-62.2],"name":"Montserrat","nativeName":"Montserrat","population":4922,"region":"Americas","subregion":"Caribbean","capital":"Plymouth","sovereignty":"GBR"},"MAR":{"a2":"MA","area":446550,"borders":["DZA","ESH","ESP"],"languages":["Arabic"],"center":[32,-5],"name":"Morocco","nativeName":"المغرب","population":33337529,"region":"Africa","subregion":"Northern Africa","capital":"Rabat"},"MOZ":{"a2":"MZ","area":801590,"borders":["MWI","ZAF","SWZ","TZA","ZMB","ZWE"],"languages":["Portuguese"],"center":[-18.25,35],"name":"Mozambique","nativeName":"Moçambique","population":26423700,"region":"Africa","subregion":"Eastern Africa","capital":"Maputo"},"MMR":{"a2":"MM","area":676578,"borders":["BGD","CHN","IND","LAO","THA"],"languages":["Burmese"],"center":[22,98],"name":"Myanmar","nativeName":"Myanma","population":51419420,"region":"Asia","subregion":"South-Eastern Asia","capital":"Nay Pyi Taw"},"NAM":{"a2":"NA","area":825615,"borders":["AGO","BWA","ZAF","ZMB"],"languages":["English","Afrikaans"],"center":[-22,17],"name":"Namibia","nativeName":"Namibia","population":2324388,"region":"Africa","subregion":"Southern Africa","capital":"Windhoek"},"NRU":{"a2":"NR","area":21,"borders":[],"languages":["English","Nauruan"],"center":[-0.53333333,166.91666666],"name":"Nauru","nativeName":"Nauru","population":10084,"region":"Oceania","subregion":"Micronesia","capital":"Yaren"},"NPL":{"a2":"NP","area":147181,"borders":["CHN","IND"],"languages":["Nepali"],"center":[28,84],"name":"Nepal","nativeName":"नेपाल","population":28431500,"region":"Asia","subregion":"Southern Asia","capital":"Kathmandu"},"NLD":{"a2":"NL","area":41850,"borders":["BEL","DEU"],"languages":["Dutch"],"center":[52.5,5.75],"name":"Netherlands","nativeName":"Nederland","population":17019800,"region":"Europe","subregion":"Western Europe","capital":"Amsterdam"},"NCL":{"a2":"NC","area":18575,"borders":[],"languages":["French"],"center":[-21.5,165.5],"name":"New Caledonia","nativeName":"Nouvelle-Calédonie","population":268767,"region":"Oceania","subregion":"Melanesia","capital":"Noumea","sovereignty":"FRA"},"NZL":{"a2":"NZ","area":270467,"borders":[],"languages":["English","Māori"],"center":[-41,174],"name":"New Zealand","nativeName":"New Zealand","population":4697854,"region":"Oceania","subregion":"Australia and New Zealand","capital":"Wellington"},"NIC":{"a2":"NI","area":130373,"borders":["CRI","HND"],"languages":["Spanish"],"center":[13,-85],"name":"Nicaragua","nativeName":"Nicaragua","population":6262703,"region":"Americas","subregion":"Central America","capital":"Managua"},"NER":{"a2":"NE","area":1267000,"borders":["DZA","BEN","BFA","TCD","LBY","MLI","NGA"],"languages":["French"],"center":[16,8],"name":"Niger","nativeName":"Niger","population":20715000,"region":"Africa","subregion":"Western Africa","capital":"Niamey"},"NGA":{"a2":"NG","area":923768,"borders":["BEN","CMR","TCD","NER"],"languages":["English"],"center":[10,8],"name":"Nigeria","nativeName":"Nigeria","population":186988000,"region":"Africa","subregion":"Western Africa","capital":"Abuja"},"NIU":{"a2":"NU","area":260,"borders":[],"languages":["English"],"center":[-19.03333333,-169.86666666],"name":"Niue","nativeName":"Niuē","population":1470,"region":"Oceania","subregion":"Polynesia","capital":"Alofi","sovereignty":"NZL"},"NFK":{"a2":"NF","area":36,"borders":[],"languages":["English"],"center":[-29.03333333,167.95],"name":"Norfolk Island","nativeName":"Norfolk Island","population":2302,"region":"Oceania","subregion":"Australia and New Zealand","capital":"Kingston","sovereignty":"AUS"},"PRK":{"a2":"KP","area":120538,"borders":["CHN","KOR","RUS"],"languages":["Korean"],"center":[40,127],"name":"North Korea","nativeName":"북한","population":25281000,"region":"Asia","subregion":"Eastern Asia","capital":"Pyongyang"},"MNP":{"a2":"MP","area":464,"borders":[],"languages":["English","Chamorro"],"center":[15.2,145.75],"name":"Northern Mariana Islands","nativeName":"Northern Mariana Islands","population":56940,"region":"Oceania","subregion":"Micronesia","capital":"Saipan","sovereignty":"USA"},"NOR":{"a2":"NO","area":323802,"borders":["FIN","SWE","RUS"],"languages":["Norwegian","Norwegian Bokmål","Norwegian Nynorsk"],"center":[62,10],"name":"Norway","nativeName":"Norge","population":5223256,"region":"Europe","subregion":"Northern Europe","capital":"Oslo"},"OMN":{"a2":"OM","area":309500,"borders":["SAU","ARE","YEM"],"languages":["Arabic"],"center":[21,57],"name":"Oman","nativeName":"عمان","population":4420133,"region":"Asia","subregion":"Western Asia","capital":"Muscat"},"PAK":{"a2":"PK","area":881912,"borders":["AFG","CHN","IND","IRN"],"languages":["English","Urdu"],"center":[30,70],"name":"Pakistan","nativeName":"Pakistan","population":194125062,"region":"Asia","subregion":"Southern Asia","capital":"Islamabad"},"PLW":{"a2":"PW","area":459,"borders":[],"languages":["English"],"center":[7.5,134.5],"name":"Palau","nativeName":"Palau","population":17950,"region":"Oceania","subregion":"Micronesia","capital":"Melekeok"},"PSE":{"a2":"PS","area":null,"borders":["ISR","EGY","JOR"],"languages":["Arabic"],"center":[31.9,35.2],"name":"Palestine","nativeName":"فلسطين","population":4682467,"region":"Asia","subregion":"Western Asia","capital":"East Jerusalem"},"PAN":{"a2":"PA","area":75417,"borders":["COL","CRI"],"languages":["Spanish"],"center":[9,-80],"name":"Panama","nativeName":"Panamá","population":3814672,"region":"Americas","subregion":"Central America","capital":"Panama City"},"PNG":{"a2":"PG","area":462840,"borders":["IDN"],"languages":["English"],"center":[-6,147],"name":"Papua New Guinea","nativeName":"Papua Niugini","population":8083700,"region":"Oceania","subregion":"Melanesia","capital":"Port Moresby"},"PRY":{"a2":"PY","area":406752,"borders":["ARG","BOL","BRA"],"languages":["Spanish","Guaraní"],"center":[-23,-58],"name":"Paraguay","nativeName":"Paraguay","population":6854536,"region":"Americas","subregion":"South America","capital":"Asuncion"},"PER":{"a2":"PE","area":1285216,"borders":["BOL","BRA","CHL","COL","ECU"],"languages":["Spanish"],"center":[-10,-76],"name":"Peru","nativeName":"Perú","population":31488700,"region":"Americas","subregion":"South America","capital":"Lima"},"PHL":{"a2":"PH","area":342353,"borders":[],"languages":["English"],"center":[13,122],"name":"Philippines","nativeName":"Pilipinas","population":103279800,"region":"Asia","subregion":"South-Eastern Asia","capital":"Manila"},"PCN":{"a2":"PN","area":47,"borders":[],"languages":["English"],"center":[-25.06666666,-130.1],"name":"Pitcairn","nativeName":"Pitcairn Islands","population":56,"region":"Oceania","subregion":"Polynesia","capital":"Adamstown","sovereignty":"GBR"},"POL":{"a2":"PL","area":312679,"borders":["BLR","CZE","DEU","LTU","RUS","SVK","UKR"],"languages":["Polish"],"center":[52,20],"name":"Poland","nativeName":"Polska","population":38437239,"region":"Europe","subregion":"Eastern Europe","capital":"Warsaw"},"PRT":{"a2":"PT","area":92090,"borders":["ESP"],"languages":["Portuguese"],"center":[39.5,-8],"name":"Portugal","nativeName":"Portugal","population":10374822,"region":"Europe","subregion":"Southern Europe","capital":"Lisbon"},"PRI":{"a2":"PR","area":8870,"borders":[],"languages":["Spanish","English"],"center":[18.25,-66.5],"name":"Puerto Rico","nativeName":"Puerto Rico","population":3474182,"region":"Americas","subregion":"Caribbean","capital":"San Juan","sovereignty":"USA"},"QAT":{"a2":"QA","area":11586,"borders":["SAU"],"languages":["Arabic"],"center":[25.5,51.25],"name":"Qatar","nativeName":"قطر","population":2587564,"region":"Asia","subregion":"Western Asia","capital":"Doha"},"XKS":{"a2":"XK","area":10908,"borders":["ALB","MKD","MNE","SRB"],"languages":["Albanian","Serbian"],"center":[42.666667,21.166667],"name":"Kosovo","nativeName":"Republika e Kosovës","population":1733842,"region":"Europe","subregion":"Eastern Europe","capital":"Pristina"},"REU":{"a2":"RE","area":null,"borders":[],"languages":["French"],"center":[-21.15,55.5],"name":"Réunion","nativeName":"La Réunion","population":840974,"region":"Africa","subregion":"Eastern Africa","capital":"Saint-Denis","sovereignty":"FRA"},"ROU":{"a2":"RO","area":238391,"borders":["BGR","HUN","MDA","SRB","UKR"],"languages":["Romanian"],"center":[46,25],"name":"Romania","nativeName":"România","population":19861408,"region":"Europe","subregion":"Eastern Europe","capital":"Bucharest"},"RUS":{"a2":"RU","area":17124442,"borders":["AZE","BLR","CHN","EST","FIN","GEO","KAZ","PRK","LVA","LTU","MNG","NOR","POL","UKR"],"languages":["Russian"],"center":[60,100],"name":"Russia","nativeName":"Россия","population":146599183,"region":"Europe","subregion":"Eastern Europe","capital":"Moscow"},"RWA":{"a2":"RW","area":26338,"borders":["BDI","COD","TZA","UGA"],"languages":["Kinyarwanda","English","French"],"center":[-2,30],"name":"Rwanda","nativeName":"Rwanda","population":11553188,"region":"Africa","subregion":"Eastern Africa","capital":"Kigali"},"BLM":{"a2":"BL","area":21,"borders":[],"languages":["French"],"center":[18.5,-63.41666666],"name":"Saint Barthélemy","nativeName":"Saint-Barthélemy","population":9417,"region":"Americas","subregion":"Caribbean","capital":"Gustavia","sovereignty":"FRA"},"SHN":{"a2":"SH","area":null,"borders":[],"languages":["English"],"center":[-15.95,-5.7],"name":"Saint Helena, Ascension and Tristan da Cunha","nativeName":"Saint Helena","population":4255,"region":"Africa","subregion":"Western Africa","capital":"Jamestown","sovereignty":"GBR"},"KNA":{"a2":"KN","area":261,"borders":[],"languages":["English"],"center":[17.33333333,-62.75],"name":"Saint Kitts and Nevis","nativeName":"Saint Kitts and Nevis","population":46204,"region":"Americas","subregion":"Caribbean","capital":"Basseterre"},"LCA":{"a2":"LC","area":616,"borders":[],"languages":["English"],"center":[13.88333333,-60.96666666],"name":"Saint Lucia","nativeName":"Saint Lucia","population":186000,"region":"Americas","subregion":"Caribbean","capital":"Castries"},"MAF":{"a2":"MF","area":53,"borders":["SXM","NLD"],"languages":["English","French","Dutch"],"center":[18.08333333,-63.95],"name":"Saint Martin (French part)","nativeName":"Saint-Martin","population":36979,"region":"Americas","subregion":"Caribbean","capital":"Marigot","sovereignty":"FRA"},"SPM":{"a2":"PM","area":242,"borders":[],"languages":["French"],"center":[46.83333333,-56.33333333],"name":"Saint Pierre and Miquelon","nativeName":"Saint-Pierre-et-Miquelon","population":6069,"region":"Americas","subregion":"Northern America","capital":"Saint-Pierre","sovereignty":"FRA"},"VCT":{"a2":"VC","area":389,"borders":[],"languages":["English"],"center":[13.25,-61.2],"name":"Saint Vincent and the Grenadines","nativeName":"Saint Vincent and the Grenadines","population":109991,"region":"Americas","subregion":"Caribbean","capital":"Kingstown"},"WSM":{"a2":"WS","area":2842,"borders":[],"languages":["Samoan","English"],"center":[-13.58333333,-172.33333333],"name":"Samoa","nativeName":"Samoa","population":194899,"region":"Oceania","subregion":"Polynesia","capital":"Apia"},"SMR":{"a2":"SM","area":61,"borders":["ITA"],"languages":["Italian"],"center":[43.76666666,12.41666666],"name":"San Marino","nativeName":"San Marino","population":33005,"region":"Europe","subregion":"Southern Europe","capital":"San Marino"},"STP":{"a2":"ST","area":964,"borders":[],"languages":["Portuguese"],"center":[1,7],"name":"Sao Tome and Principe","nativeName":"São Tomé e Príncipe","population":187356,"region":"Africa","subregion":"Middle Africa","capital":"Sao Tome"},"SAU":{"a2":"SA","area":2149690,"borders":["IRQ","JOR","KWT","OMN","QAT","ARE","YEM"],"languages":["Arabic"],"center":[25,45],"name":"Saudi Arabia","nativeName":"العربية السعودية","population":32248200,"region":"Asia","subregion":"Western Asia","capital":"Riyadh"},"SEN":{"a2":"SN","area":196722,"borders":["GMB","GIN","GNB","MLI","MRT"],"languages":["French"],"center":[14,-14],"name":"Senegal","nativeName":"Sénégal","population":14799859,"region":"Africa","subregion":"Western Africa","capital":"Dakar"},"SRB":{"a2":"RS","area":88361,"borders":["BIH","BGR","HRV","HUN","XKS","MKD","MNE","ROU"],"languages":["Serbian"],"center":[44,21],"name":"Serbia","nativeName":"Србија","population":7076372,"region":"Europe","subregion":"Southern Europe","capital":"Belgrade"},"SYC":{"a2":"SC","area":452,"borders":[],"languages":["French","English"],"center":[-4.58333333,55.66666666],"name":"Seychelles","nativeName":"Seychelles","population":91400,"region":"Africa","subregion":"Eastern Africa","capital":"Victoria"},"SLE":{"a2":"SL","area":71740,"borders":["GIN","LBR"],"languages":["English"],"center":[8.5,-11.5],"name":"Sierra Leone","nativeName":"Sierra Leone","population":7075641,"region":"Africa","subregion":"Western Africa","capital":"Freetown"},"SGP":{"a2":"SG","area":710,"borders":[],"languages":["English","Malay","Tamil","Chinese"],"center":[1.36666666,103.8],"name":"Singapore","nativeName":"Singapore","population":5535000,"region":"Asia","subregion":"South-Eastern Asia","capital":"Singapore"},"SXM":{"a2":"SX","area":34,"borders":["MAF"],"languages":["Dutch","English"],"center":[18.033333,-63.05],"name":"Saint Marten (Dutch part)","nativeName":"Saint Marten","population":38247,"region":"Americas","subregion":"Caribbean","capital":"Philipsburg","sovereignty":"NLD"},"SVK":{"a2":"SK","area":49037,"borders":["AUT","CZE","HUN","POL","UKR"],"languages":["Slovak"],"center":[48.66666666,19.5],"name":"Slovakia","nativeName":"Slovensko","population":5426252,"region":"Europe","subregion":"Eastern Europe","capital":"Bratislava"},"SVN":{"a2":"SI","area":20273,"borders":["AUT","HRV","ITA","HUN"],"languages":["Slovene"],"center":[46.11666666,14.81666666],"name":"Slovenia","nativeName":"Slovenija","population":2064188,"region":"Europe","subregion":"Southern Europe","capital":"Ljubljana"},"SLB":{"a2":"SB","area":28896,"borders":[],"languages":["English"],"center":[-8,159],"name":"Solomon Islands","nativeName":"Solomon Islands","population":642000,"region":"Oceania","subregion":"Melanesia","capital":"Honiara"},"SOM":{"a2":"SO","area":637657,"borders":["DJI","ETH","KEN"],"languages":["Somali","Arabic"],"center":[10,49],"name":"Somalia","nativeName":"Soomaaliya","population":11079000,"region":"Africa","subregion":"Eastern Africa","capital":"Mogadishu"},"ZAF":{"a2":"ZA","area":1221037,"borders":["BWA","LSO","MOZ","NAM","SWZ","ZWE"],"languages":["Afrikaans","English","Southern Ndebele","Southern Sotho","Swati","Tswana","Tsonga","Venda","Xhosa","Zulu"],"center":[-29,24],"name":"South Africa","nativeName":"South Africa","population":55653654,"region":"Africa","subregion":"Southern Africa","capital":"Pretoria"},"SGS":{"a2":"GS","area":null,"borders":[],"languages":["English"],"center":[-54.5,-37],"name":"South Georgia and the South Sandwich Islands","nativeName":"South Georgia","population":30,"region":"Americas","subregion":"South America","capital":"Grytviken","sovereignty":"GBR"},"KOR":{"a2":"KR","area":100210,"borders":["PRK"],"languages":["Korean"],"center":[37,127.5],"name":"South Korea","nativeName":"대한민국","population":50801405,"region":"Asia","subregion":"Eastern Asia","capital":"Seoul"},"SSD":{"a2":"SS","area":619745,"borders":["CAF","COD","ETH","KEN","SDN","UGA"],"languages":["English"],"center":[7,30],"name":"South Sudan","nativeName":"South Sudan","population":12131000,"region":"Africa","subregion":"Middle Africa","capital":"Juba"},"ESP":{"a2":"ES","area":505992,"borders":["AND","FRA","GIB","PRT","MAR"],"languages":["Spanish"],"center":[40,-4],"name":"Spain","nativeName":"España","population":46438422,"region":"Europe","subregion":"Southern Europe","capital":"Madrid"},"LKA":{"a2":"LK","area":65610,"borders":["IND"],"languages":["Sinhalese","Tamil"],"center":[7,81],"name":"Sri Lanka","nativeName":"śrī laṃkāva","population":20966000,"region":"Asia","subregion":"Southern Asia","capital":"Colombo"},"SDN":{"a2":"SD","area":1886068,"borders":["CAF","TCD","EGY","ERI","ETH","LBY","SSD"],"languages":["Arabic","English"],"center":[15,30],"name":"Sudan","nativeName":"السودان","population":39598700,"region":"Africa","subregion":"Northern Africa","capital":"Khartoum"},"SUR":{"a2":"SR","area":163820,"borders":["BRA","GUF","FRA","GUY"],"languages":["Dutch"],"center":[4,-56],"name":"Suriname","nativeName":"Suriname","population":541638,"region":"Americas","subregion":"South America","capital":"Paramaribo"},"SWZ":{"a2":"SZ","area":17364,"borders":["MOZ","ZAF"],"languages":["English","Swati"],"center":[-26.5,31.5],"name":"Eswatini","nativeName":"Eswatini","population":1132657,"region":"Africa","subregion":"Southern Africa","capital":"Mbabane"},"SWE":{"a2":"SE","area":450295,"borders":["FIN","NOR"],"languages":["Swedish"],"center":[62,15],"name":"Sweden","nativeName":"Sverige","population":9894888,"region":"Europe","subregion":"Northern Europe","capital":"Stockholm"},"CHE":{"a2":"CH","area":41284,"borders":["AUT","FRA","ITA","LIE","DEU"],"languages":["German","French","Italian"],"center":[47,8],"name":"Switzerland","nativeName":"Schweiz","population":8341600,"region":"Europe","subregion":"Western Europe","capital":"Berne"},"SYR":{"a2":"SY","area":185180,"borders":["IRQ","ISR","JOR","LBN","TUR"],"languages":["Arabic"],"center":[35,38],"name":"Syria","nativeName":"سوريا","population":18564000,"region":"Asia","subregion":"Western Asia","capital":"Damascus"},"TWN":{"a2":"TW","area":36193,"borders":[],"languages":["Chinese"],"center":[23.5,121],"name":"Taiwan","nativeName":"臺灣","population":23503349,"region":"Asia","subregion":"Eastern Asia","capital":"Taipei"},"TJK":{"a2":"TJ","area":143100,"borders":["AFG","CHN","KGZ","UZB"],"languages":["Tajik","Russian"],"center":[39,71],"name":"Tajikistan","nativeName":"Тоҷикистон","population":8593600,"region":"Asia","subregion":"Central Asia","capital":"Dushanbe"},"TZA":{"a2":"TZ","area":945087,"borders":["BDI","COD","KEN","MWI","MOZ","RWA","UGA","ZMB"],"languages":["Swahili","English"],"center":[-6,35],"name":"Tanzania","nativeName":"Tanzania","population":55155000,"region":"Africa","subregion":"Eastern Africa","capital":"Dodoma"},"THA":{"a2":"TH","area":513120,"borders":["MMR","KHM","LAO","MYS"],"languages":["Thai"],"center":[15,100],"name":"Thailand","nativeName":"ประเทศไทย","population":65327652,"region":"Asia","subregion":"South-Eastern Asia","capital":"Bangkok"},"TLS":{"a2":"TL","area":14874,"borders":["IDN"],"languages":["Portuguese"],"center":[-8.83333333,125.91666666],"name":"Timor-Leste","nativeName":"Timor-Leste","population":1167242,"region":"Asia","subregion":"South-Eastern Asia","capital":"Dili"},"TGO":{"a2":"TG","area":56785,"borders":["BEN","BFA","GHA"],"languages":["French"],"center":[8,1.16666666],"name":"Togo","nativeName":"Togo","population":7143000,"region":"Africa","subregion":"Western Africa","capital":"Lome"},"TKL":{"a2":"TK","area":12,"borders":[],"languages":["English"],"center":[-9,-172],"name":"Tokelau","nativeName":"Tokelau","population":1411,"region":"Oceania","subregion":"Polynesia","capital":"Nukunonu","sovereignty":"NZL"},"TON":{"a2":"TO","area":747,"borders":[],"languages":["English","Tonga (Tonga Islands)"],"center":[-20,-175],"name":"Tonga","nativeName":"Tonga","population":103252,"region":"Oceania","subregion":"Polynesia","capital":"Nuku'alofa"},"TTO":{"a2":"TT","area":5130,"borders":[],"languages":["English"],"center":[11,-61],"name":"Trinidad and Tobago","nativeName":"Trinidad and Tobago","population":1349667,"region":"Americas","subregion":"Caribbean","capital":"Port of Spain"},"TUN":{"a2":"TN","area":163610,"borders":["DZA","LBY"],"languages":["Arabic"],"center":[34,9],"name":"Tunisia","nativeName":"تونس","population":11154400,"region":"Africa","subregion":"Northern Africa","capital":"Tunis"},"TUR":{"a2":"TR","area":783562,"borders":["ARM","AZE","BGR","GEO","GRC","IRN","IRQ","SYR"],"languages":["Turkish"],"center":[39,35],"name":"Turkey","nativeName":"Türkiye","population":78741053,"region":"Asia","subregion":"Western Asia","capital":"Ankara"},"TKM":{"a2":"TM","area":488100,"borders":["AFG","IRN","KAZ","UZB"],"languages":["Turkmen","Russian"],"center":[40,60],"name":"Turkmenistan","nativeName":"Türkmenistan","population":4751120,"region":"Asia","subregion":"Central Asia","capital":"Ashgabat"},"TCA":{"a2":"TC","area":948,"borders":[],"languages":["English"],"center":[21.75,-71.58333333],"name":"Turks and Caicos Islands","nativeName":"Turks and Caicos Islands","population":31458,"region":"Americas","subregion":"Caribbean","capital":"Cockburn Town","sovereignty":"GBR"},"TUV":{"a2":"TV","area":26,"borders":[],"languages":["English"],"center":[-8,178],"name":"Tuvalu","nativeName":"Tuvalu","population":10640,"region":"Oceania","subregion":"Polynesia","capital":"Funafuti"},"UGA":{"a2":"UG","area":241550,"borders":["COD","KEN","RWA","SSD","TZA"],"languages":["English","Swahili"],"center":[1,32],"name":"Uganda","nativeName":"Uganda","population":33860700,"region":"Africa","subregion":"Eastern Africa","capital":"Kampala"},"UKR":{"a2":"UA","area":603700,"borders":["BLR","HUN","MDA","POL","ROU","RUS","SVK"],"languages":["Ukrainian"],"center":[49,32],"name":"Ukraine","nativeName":"Україна","population":42692393,"region":"Europe","subregion":"Eastern Europe","capital":"Kiev"},"ARE":{"a2":"AE","area":83600,"borders":["OMN","SAU"],"languages":["Arabic"],"center":[24,54],"name":"United Arab Emirates","nativeName":"دولة الإمارات العربية المتحدة","population":9856000,"region":"Asia","subregion":"Western Asia","capital":"Abu Dhabi"},"GBR":{"a2":"GB","area":242900,"borders":["IRL"],"languages":["English"],"center":[54,-2],"name":"United Kingdom","nativeName":"United Kingdom","population":65110000,"region":"Europe","subregion":"Northern Europe","capital":"London"},"USA":{"a2":"US","area":9629091,"borders":["CAN","MEX"],"languages":["English"],"center":[38,-97],"name":"United States of America","nativeName":"United States","population":323947000,"region":"Americas","subregion":"Northern America","capital":"Washington"},"URY":{"a2":"UY","area":181034,"borders":["ARG","BRA"],"languages":["Spanish"],"center":[-33,-56],"name":"Uruguay","nativeName":"Uruguay","population":3480222,"region":"Americas","subregion":"South America","capital":"Montevideo"},"UZB":{"a2":"UZ","area":447400,"borders":["AFG","KAZ","KGZ","TJK","TKM"],"languages":["Uzbek","Russian"],"center":[41,64],"name":"Uzbekistan","nativeName":"O‘zbekiston","population":31576400,"region":"Asia","subregion":"Central Asia","capital":"Tashkent"},"VUT":{"a2":"VU","area":12189,"borders":[],"languages":["Bislama","English","French"],"center":[-16,167],"name":"Vanuatu","nativeName":"Vanuatu","population":277500,"region":"Oceania","subregion":"Melanesia","capital":"Port Vila"},"VEN":{"a2":"VE","area":916445,"borders":["BRA","COL","GUY"],"languages":["Spanish"],"center":[8,-66],"name":"Venezuela","nativeName":"Venezuela","population":31028700,"region":"Americas","subregion":"South America","capital":"Caracas"},"VNM":{"a2":"VN","area":331212,"borders":["KHM","CHN","LAO"],"languages":["Vietnamese"],"center":[16.16666666,107.83333333],"name":"Vietnam","nativeName":"Việt Nam","population":92700000,"region":"Asia","subregion":"South-Eastern Asia","capital":"Hanoi"},"WLF":{"a2":"WF","area":142,"borders":[],"languages":["French"],"center":[-13.3,-176.2],"name":"Wallis and Futuna","nativeName":"Wallis et Futuna","population":11750,"region":"Oceania","subregion":"Polynesia","capital":"Mata Utu","sovereignty":"FRA"},"ESH":{"a2":"EH","area":266000,"borders":["DZA","MRT","MAR"],"languages":["Spanish"],"center":[24.5,-13],"name":"Western Sahara","nativeName":"الصحراء الغربية","population":510713,"region":"Africa","subregion":"Northern Africa","capital":"El-Aaiun","sovereignty":"MAR"},"YEM":{"a2":"YE","area":527968,"borders":["OMN","SAU"],"languages":["Arabic"],"center":[15,48],"name":"Yemen","nativeName":"اليَمَن","population":27478000,"region":"Asia","subregion":"Western Asia","capital":"Sanaa"},"ZMB":{"a2":"ZM","area":752612,"borders":["AGO","BWA","COD","MWI","MOZ","NAM","TZA","ZWE"],"languages":["English"],"center":[-15,30],"name":"Zambia","nativeName":"Zambia","population":15933883,"region":"Africa","subregion":"Eastern Africa","capital":"Lusaka"},"ZWE":{"a2":"ZW","area":390757,"borders":["BWA","MOZ","ZAF","ZMB"],"languages":["English","Shona","Northern Ndebele"],"center":[-20,30],"name":"Zimbabwe","nativeName":"Zimbabwe","population":14240168,"region":"Africa","subregion":"Eastern Africa","capital":"Harare"},"SJM":{"a2":"SJ","area":62045,"borders":[],"languages":["Norwegian","Norwegian Bokmål","Norwegian Nynorsk"],"center":[78,17],"name":"Svalbard","nativeName":"Svalbard","population":2504,"region":"Europe","subregion":"Northern Europe","capital":"Longyearbyen","sovereignty":"NOR"}}